{
  "type": "Program",
  "body": [
    {
      "type": "ExpressionStatement",
      "expression": {
        "type": "Literal",
        "value": "use strict",
        "raw": "'use strict'",
        "range": [
          0,
          12
        ],
        "loc": {
          "start": {
            "line": 1,
            "column": 0
          },
          "end": {
            "line": 1,
            "column": 12
          }
        }
      },
      "range": [
        0,
        13
      ],
      "loc": {
        "start": {
          "line": 1,
          "column": 0
        },
        "end": {
          "line": 1,
          "column": 13
        }
      }
    },
    {
      "type": "ImportDeclaration",
      "specifiers": [
        {
          "type": "ImportDefaultSpecifier",
          "local": {
            "type": "Identifier",
            "name": "Queue",
            "range": [
              22,
              27
            ],
            "loc": {
              "start": {
                "line": 3,
                "column": 7
              },
              "end": {
                "line": 3,
                "column": 12
              }
            }
          },
          "range": [
            22,
            27
          ],
          "loc": {
            "start": {
              "line": 3,
              "column": 7
            },
            "end": {
              "line": 3,
              "column": 12
            }
          }
        }
      ],
      "source": {
        "type": "Literal",
        "value": "./queue",
        "raw": "'./queue'",
        "range": [
          33,
          42
        ],
        "loc": {
          "start": {
            "line": 3,
            "column": 18
          },
          "end": {
            "line": 3,
            "column": 27
          }
        }
      },
      "range": [
        15,
        43
      ],
      "loc": {
        "start": {
          "line": 3,
          "column": 0
        },
        "end": {
          "line": 3,
          "column": 28
        }
      }
    },
    {
      "type": "ImportDeclaration",
      "specifiers": [
        {
          "type": "ImportDefaultSpecifier",
          "local": {
            "type": "Identifier",
            "name": "LogIndexFile",
            "range": [
              51,
              63
            ],
            "loc": {
              "start": {
                "line": 4,
                "column": 7
              },
              "end": {
                "line": 4,
                "column": 19
              }
            }
          },
          "range": [
            51,
            63
          ],
          "loc": {
            "start": {
              "line": 4,
              "column": 7
            },
            "end": {
              "line": 4,
              "column": 19
            }
          }
        }
      ],
      "source": {
        "type": "Literal",
        "value": "./log-index-file",
        "raw": "'./log-index-file'",
        "range": [
          69,
          87
        ],
        "loc": {
          "start": {
            "line": 4,
            "column": 25
          },
          "end": {
            "line": 4,
            "column": 43
          }
        }
      },
      "range": [
        44,
        88
      ],
      "loc": {
        "start": {
          "line": 4,
          "column": 0
        },
        "end": {
          "line": 4,
          "column": 44
        }
      }
    },
    {
      "type": "ImportDeclaration",
      "specifiers": [
        {
          "type": "ImportDefaultSpecifier",
          "local": {
            "type": "Identifier",
            "name": "WriteAheadLog",
            "range": [
              96,
              109
            ],
            "loc": {
              "start": {
                "line": 5,
                "column": 7
              },
              "end": {
                "line": 5,
                "column": 20
              }
            }
          },
          "range": [
            96,
            109
          ],
          "loc": {
            "start": {
              "line": 5,
              "column": 7
            },
            "end": {
              "line": 5,
              "column": 20
            }
          }
        }
      ],
      "source": {
        "type": "Literal",
        "value": "./write-ahead-log",
        "raw": "'./write-ahead-log'",
        "range": [
          115,
          134
        ],
        "loc": {
          "start": {
            "line": 5,
            "column": 26
          },
          "end": {
            "line": 5,
            "column": 45
          }
        }
      },
      "range": [
        89,
        135
      ],
      "loc": {
        "start": {
          "line": 5,
          "column": 0
        },
        "end": {
          "line": 5,
          "column": 46
        }
      }
    },
    {
      "type": "ExportNamedDeclaration",
      "declaration": null,
      "specifiers": [
        {
          "type": "ExportSpecifier",
          "exported": {
            "type": "Identifier",
            "name": "Queue",
            "range": [
              146,
              151
            ],
            "loc": {
              "start": {
                "line": 7,
                "column": 9
              },
              "end": {
                "line": 7,
                "column": 14
              }
            }
          },
          "local": {
            "type": "Identifier",
            "name": "Queue",
            "range": [
              146,
              151
            ],
            "loc": {
              "start": {
                "line": 7,
                "column": 9
              },
              "end": {
                "line": 7,
                "column": 14
              }
            }
          },
          "range": [
            146,
            151
          ],
          "loc": {
            "start": {
              "line": 7,
              "column": 9
            },
            "end": {
              "line": 7,
              "column": 14
            }
          }
        },
        {
          "type": "ExportSpecifier",
          "exported": {
            "type": "Identifier",
            "name": "LogIndexFile",
            "range": [
              153,
              165
            ],
            "loc": {
              "start": {
                "line": 7,
                "column": 16
              },
              "end": {
                "line": 7,
                "column": 28
              }
            }
          },
          "local": {
            "type": "Identifier",
            "name": "LogIndexFile",
            "range": [
              153,
              165
            ],
            "loc": {
              "start": {
                "line": 7,
                "column": 16
              },
              "end": {
                "line": 7,
                "column": 28
              }
            }
          },
          "range": [
            153,
            165
          ],
          "loc": {
            "start": {
              "line": 7,
              "column": 16
            },
            "end": {
              "line": 7,
              "column": 28
            }
          }
        },
        {
          "type": "ExportSpecifier",
          "exported": {
            "type": "Identifier",
            "name": "WriteAheadLog",
            "range": [
              167,
              180
            ],
            "loc": {
              "start": {
                "line": 7,
                "column": 30
              },
              "end": {
                "line": 7,
                "column": 43
              }
            }
          },
          "local": {
            "type": "Identifier",
            "name": "WriteAheadLog",
            "range": [
              167,
              180
            ],
            "loc": {
              "start": {
                "line": 7,
                "column": 30
              },
              "end": {
                "line": 7,
                "column": 43
              }
            }
          },
          "range": [
            167,
            180
          ],
          "loc": {
            "start": {
              "line": 7,
              "column": 30
            },
            "end": {
              "line": 7,
              "column": 43
            }
          }
        }
      ],
      "source": null,
      "range": [
        137,
        183
      ],
      "loc": {
        "start": {
          "line": 7,
          "column": 0
        },
        "end": {
          "line": 7,
          "column": 46
        }
      }
    }
  ],
  "sourceType": "module",
  "range": [
    0,
    183
  ],
  "loc": {
    "start": {
      "line": 1,
      "column": 0
    },
    "end": {
      "line": 7,
      "column": 46
    }
  },
  "comments": []
}